classify/__init__.py
classify/formatters.py
classify/library.py
classify/main.py
classify/contrib/__init__.py
classify/contrib/django/__init__.py
classify/contrib/django/settings.py
classify/templates/web.html
classify-0.5.0.data/scripts/classify
classify-0.5.0.dist-info/DESCRIPTION.rst
classify-0.5.0.dist-info/entry_points.txt
classify-0.5.0.dist-info/METADATA
classify-0.5.0.dist-info/pydist.json
classify-0.5.0.dist-info/RECORD
classify-0.5.0.dist-info/top_level.txt
classify-0.5.0.dist-info/WHEEL
