Metadata-Version: 1.0
Name: classify
Version: 0.5.0
Summary: Generate concrete Class documentation for Python Classes.
Home-page: http://github.com/ghickman/classify
Author: George Hickman
Author-email: george@ghickman.co.uk
License: MIT
Platform: UNKNOWN
Classifier: Development Status :: 4 - Beta
Classifier: Intended Audience :: Developers
Classifier: License :: OSI Approved :: MIT License
Classifier: Operating System :: MacOS :: MacOS X
Classifier: Operating System :: POSIX
Classifier: Programming Language :: Python :: 2.6
Classifier: Programming Language :: Python :: 2.7
Classifier: Topic :: Documentation
